[{"id":1,"agence":9,"numContrat":"CTR-00001","dateContrat":"04\/07\/2023","bailleur":"SITRAKA THIERRY","bail":"VILLA FLEUR","locataire":"JEAN MARC","cycle":"Mensuel","dateDebut":"04\/07\/2023","dateFin":"30\/06\/2024","dureeContrat":"1 An(s)","montantContrat":3425806.45,"statut":"En Cours"},{"id":2,"agence":9,"numContrat":"CTR-00002","dateContrat":"07\/07\/2023","bailleur":"SITRAKA THIERRY","bail":"VILLA FLEUR","locataire":"JEAN MARC","cycle":"Journalier","dateDebut":"07\/07\/2023","dateFin":"21\/08\/2023","dureeContrat":"45 Jour(s)","montantContrat":450000,"statut":"En Cours"},{"id":3,"agence":9,"numContrat":"CTR-00003","dateContrat":"07\/07\/2023","bailleur":"SITRAKA THIERRY","bail":"VILLA MAMISOA","locataire":"LAURENNE","cycle":"Mensuel","dateDebut":"04\/04\/2023","dateFin":"03\/04\/2024","dureeContrat":"1 An(s)","montantContrat":7500000,"statut":"En Cours"},{"id":4,"agence":9,"numContrat":"CTR-00004","dateContrat":"09\/07\/2023","bailleur":"SITRAKA THIERRY","bail":"VILLA FLEUR","locataire":"JEAN MARC","cycle":"Journalier","dateDebut":"04\/06\/2023","dateFin":"19\/07\/2023","dureeContrat":"45 Jour(s)","montantContrat":300000,"statut":"En Cours"}]